CAE_01/my_2inmux.v
module my_nand ( A, B, S, R);
    input A, B, S;
    output R;

    assign  R = ((A & ~S) | (S & B));
endmodule

CAE_01/test_my_2inmux.v
module test_my_2inmux;
reg a, b, s;
wire out;
my_nand ma1 (a, b, s, out);
initial begin
    $dumpfile("test_my_2inmux.vcd");
    $dumpvars(0, test_my_2inmux);
    $monitor ("%t: a =%b, b =%b, s=%d, out = %b", $time, a, b, s, out);
    a = 0; b = 0;
    #10 a = 1;
    #10 a = 0; b = 1;
    #10 a = 1;
    #10 a = 0; b = 0;
    #10 $finish;
end
endmodule

CAE_01/test_my_2inmux.vcd
$date
	Tue May 15 15:52:57 2018
$end
$version
	Icarus Verilog
$end
$timescale
	1s
$end
$scope module test_my_2inmux $end
$var wire 1 ! out $end
$var reg 1 " a $end
$var reg 1 # b $end
$var reg 1 $ s $end
$scope module ma1 $end
$var wire 1 " A $end
$var wire 1 # B $end
$var wire 1 ! R $end
$var wire 1 $ S $end
$upscope $end
$upscope $end
$enddefinitions $end
#0
$dumpvars
0$
0#
0"
0!
$end
#10
1#
#20
1!
0#
1"
#30
1#
#40
0!
0#
0"
1$
#50
1!
1#
#60
0!
0#
1"
#70
1!
1#
