CAE_11/led7seg9.v
module led7seg9 (I,LED,SA);
    input [3:0]I;
    output [7:0]LED;
    output [3:0]SA;

    assign  SA = 4'bZZZ0;
    assign  LED[0] = (~I[0] & I[1] & I[2] & I[3] )^(I[0] & I[1] & ~I[2] & I[3])^(I[0] & ~I[1] & ~I[2] & I[3]);
    assign  LED[1] = (~I[0] & I[1] & ~I[2] & I[3])^(I[0] & ~I[1] & ~I[2] & I[3]);
    assign  LED[2] = I[0] & ~I[1] &I[2] & I[3];
    assign  LED[3] = (~I[0] & I[1] &I[2] & I[3])^(I[0] & I[1] & ~I[2] & I[3])^(~I[0] & I[1] &I[2] & ~I[3]);
    assign  LED[4] = (~I[0] & I[1]) ^ (~I[0] & ~I[1]) ^ (I[0] & I[1] & ~I[2] & I[3]);
    assign  LED[5] = (~I[0] & I[1] &I[2] & I[3]) ^ (~I[0] & ~I[1]) ^ (~I[1] & I[2] & I[3]);
    assign  LED[6] = I[1];
    assign  LED[7] = 1'b1;
endmodule

CAE_11/test_leg7seg9.v
module test_led7seg;
reg [3:0]I;
wire [7:0]LED;
wire [3:0]SA;
led7seg9 ma1 (I, LED,SA);
initial begin
    $dumpfile("test_led7seg.vcd");
    $dumpvars(0, test_led7seg);
    $monitor ("%t: I =%b, LED[0] =%b, LED[1] =%b, LED[2] =%b, LED[3] =%b, LED[4] =%b, LED[5] =%b, LED[6] =%b", $time, I, LED[0],LED[1], LED[2], LED[3], LED[4], LED[5], LED[6]);
    I = 4'b1111;
    #10 I = 4'b1110;
    #10 I = 4'b1101;
    #10 I = 4'b1100;
    #10 I = 4'b1011;
    #10 I = 4'b1010;
    #10 I = 4'b1001;
    #10 I = 4'b1000;
    #10 I = 4'b0111;
    #10 I = 4'b0110;
    #10 I = 4'b0101;
    #10 I = 4'b0100;
    #10 I = 4'b0011;
    #10 I = 4'b0010;
    #10 I = 4'b0001;
    #10 I = 4'b0000;
    #10 $finish;
end
endmodule

CAE_11/test_led7seg.vcd
$date
	Wed Jun 27 00:56:32 2018
$end
$version
	Icarus Verilog
$end
$timescale
	1s
$end
$scope module test_led7seg $end
$var wire 4 ! SA [3:0] $end
$var wire 8 " LED [7:0] $end
$var reg 4 # I [3:0] $end
$scope module ma1 $end
$var wire 4 $ I [3:0] $end
$var wire 4 % SA [3:0] $end
$var wire 8 & LED [7:0] $end
$upscope $end
$upscope $end
$enddefinitions $end
#0
$dumpvars
b11000000 &
bz0 %
b1111 $
b1111 #
b11000000 "
bz0 !
$end
#10
b11111001 "
b11111001 &
b1110 #
b1110 $
#20
b10100100 "
b10100100 &
b1101 #
b1101 $
#30
b10010000 "
b10010000 &
b1100 #
b1100 $
#40
b11011001 "
b11011001 &
b1011 #
b1011 $
#50
b11010010 "
b11010010 &
b1010 #
b1010 $
#60
b10000011 "
b10000011 &
b1001 #
b1001 $
#70
b10110000 "
b10110000 &
b1000 #
b1000 $
#80
b11000000 "
b11000000 &
b111 #
b111 $
#90
b11011000 "
b11011000 &
b110 #
b110 $
#100
b10000000 "
b10000000 &
b101 #
b101 $
#110
b10110000 "
b10110000 &
b100 #
b100 $
#120
b11000000 "
b11000000 &
b11 #
b11 $
#130
b11010000 "
b11010000 &
b10 #
b10 $
#140
b10000000 "
b10000000 &
b1 #
b1 $
#150
b10110000 "
b10110000 &
b0 #
b0 $
